Sevenpack-2.7.1.data/scripts/sixpack
Sevenpack-2.7.1.data/scripts/sixpack-web
sixpack/__init__.py
sixpack/analysis.py
sixpack/api.py
sixpack/config.py
sixpack/db.py
sixpack/metrics.py
sixpack/models.py
sixpack/server.py
sixpack/utils.py
sixpack/web.py
sixpack/static/.webassets-cache/.gitkeep
sixpack/static/css/sixpack.css
sixpack/static/css/vendor/bootstrap-responsive.css
sixpack/static/css/vendor/bootstrap-responsive.min.css
sixpack/static/css/vendor/bootstrap.css
sixpack/static/css/vendor/bootstrap.min.css
sixpack/static/flash/ZeroClipboard.swf
sixpack/static/gen/.gitkeep
sixpack/static/img/background-gradient.png
sixpack/static/img/background-tile.png
sixpack/static/img/favicon.png
sixpack/static/img/glyphicons-halflings-white.png
sixpack/static/img/glyphicons-halflings.png
sixpack/static/img/logo.png
sixpack/static/img/logo@2x.png
sixpack/static/js/chart.js
sixpack/static/js/experiment.js
sixpack/static/js/sixpack.js
sixpack/static/js/vendor/bootstrap.js
sixpack/static/js/vendor/bootstrap.min.js
sixpack/static/js/vendor/d3.js
sixpack/static/js/vendor/jquery.js
sixpack/static/js/vendor/spin.min.js
sixpack/static/js/vendor/underscore-min.js
sixpack/static/js/vendor/waypoints.min.js
sixpack/static/js/vendor/zeroclipboard.min.js
sixpack/templates/dashboard.html
sixpack/templates/details.html
sixpack/templates/layout.html
sixpack/templates/errors/404.html
sixpack/templates/errors/500.html
sixpack/test/__init__.py
sixpack/test/alternative_choice_test.py
sixpack/test/alternative_model_test.py
sixpack/test/api_test.py
sixpack/test/bot_detection_test.py
sixpack/test/experiment_lua_test.py
sixpack/test/experiment_model_test.py
sixpack/test/server_logic_test.py
sixpack/test/server_metrics_test.py
sixpack/test/server_test.py
sixpack/test/utils_test.py
Sevenpack-2.7.1.dist-info/LICENSE.txt
Sevenpack-2.7.1.dist-info/METADATA
Sevenpack-2.7.1.dist-info/WHEEL
Sevenpack-2.7.1.dist-info/top_level.txt
Sevenpack-2.7.1.dist-info/RECORD
