Metadata-Version: 2.1
Name: Sevenpack
Version: 2.7.1
Summary: UNKNOWN
Home-page: http://github.com/seatgeek/sixpack
Author: SeatGeek
Author-email: hi@seatgeek.com
License: Copyright (c) 2015, SeatGeek, Inc.
Requires-Dist: closure (==20121212)
Requires-Dist: decorator (==3.3.2)
Requires-Dist: fakeredis (==1.4.3)
Requires-Dist: Flask-Assets (==2.0)
Requires-Dist: Flask-DebugToolbar (==0.7.1)
Requires-Dist: Flask-SeaSurf (==0.1.13)
Requires-Dist: Flask-Cors (==2.0.1)
Requires-Dist: Flask (==1.0)
Requires-Dist: gevent (==20.6.2)
Requires-Dist: gunicorn (<=19.4.1,>=17.5)
Requires-Dist: hiredis (==0.1.4)
Requires-Dist: jsmin (==2.0.2-1)
Requires-Dist: Markdown (==3.2.2)
Requires-Dist: mock (==1.0.1)
Requires-Dist: python-coveralls (==2.4.3)
Requires-Dist: python-dateutil (==1.5)
Requires-Dist: PyYAML (==5.1)
Requires-Dist: redis (==3.5.3)
Requires-Dist: statsd (==3.2.1)
Requires-Dist: webassets (==2.0)
Requires-Dist: Werkzeug (==0.15.3)
